MANIFEST.in
README.rst
bootstrap.py
buildout.cfg
setup.py
xbob/__init__.py
xbob.sox.egg-info/PKG-INFO
xbob.sox.egg-info/SOURCES.txt
xbob.sox.egg-info/dependency_links.txt
xbob.sox.egg-info/entry_points.txt
xbob.sox.egg-info/namespace_packages.txt
xbob.sox.egg-info/not-zip-safe
xbob.sox.egg-info/requires.txt
xbob.sox.egg-info/top_level.txt
xbob/sox/__init__.py
xbob/sox/test.py
xbob/sox/data/sample1.sph
xbob/sox/data/sample1.wav
xbob/sox/data/sample3.mat
xbob/sox/data/sample3.wav
xbob/sox/data/sample4.wav
xbob/sox/ext/ext.cc
xbob/sox/ext/reader.cc
xbob/sox/ext/reader.h
xbob/sox/ext/utilities.cc
xbob/sox/ext/utilities.h
xbob/sox/ext/writer.cc
xbob/sox/ext/writer.h