Metadata-Version: 1.1
Name: xbob.sox
Version: 1.0.0
Summary: Audio reader and writer using sox for bob and python
Home-page: http://pypi.python.org/pypi/xbob.sox
Author: Elie Khoury
Author-email: elie.khoury@idiap.ch
License: GPLv3
Platform: UNKNOWN
Classifier: Development Status :: 4 - Beta
Classifier: Intended Audience :: Developers
Classifier: License :: OSI Approved :: GNU General Public License v3 (GPLv3)
Classifier: Natural Language :: English
Classifier: Programming Language :: Python
Classifier: Topic :: Scientific/Engineering :: Artificial Intelligence
